transductor/__init__.py
transductor/transductor.py
transductor-0.1.dist-info/METADATA
transductor-0.1.dist-info/RECORD
transductor-0.1.dist-info/WHEEL
transductor-0.1.dist-info/top_level.txt
