Metadata-Version: 2.1
Name: transductor
Version: 0.1
Summary: a minimalistic library for processing, parsing and transforming texts in python
Home-page: UNKNOWN
Author: Bertrand Nouvel
Author-email: UNKNOWN
License: UNKNOWN
Platform: UNKNOWN
